pylongslit/__init__.py
pylongslit/check_config.py
pylongslit/combine.py
pylongslit/combine_2d.py
pylongslit/combine_arcs.py
pylongslit/crop.py
pylongslit/crremoval.py
pylongslit/dark.py
pylongslit/extract_1d.py
pylongslit/extract_simple_1d.py
pylongslit/flux_calibrate.py
pylongslit/identify.py
pylongslit/logger.py
pylongslit/mkspecbias.py
pylongslit/mkspecflat.py
pylongslit/obj_trace.py
pylongslit/obj_trace_clone.py
pylongslit/obj_trace_manual.py
pylongslit/overscan.py
pylongslit/parser.py
pylongslit/reduce.py
pylongslit/sensitivity_function.py
pylongslit/skysubtract.py
pylongslit/spec_viewer.py
pylongslit/stats.py
pylongslit/subtract_background.py
pylongslit/utils.py
pylongslit/version.py
pylongslit/wavecalib.py
pylongslit/tests/GQ1218+0832.json
pylongslit/tests/README.md
pylongslit/tests/SDSS_J213510+2728.json
pylongslit/tests/test_2dspec.py
pylongslit/tests/test_AB_subtract.py
pylongslit/tests/test_bias.py
pylongslit/tests/test_combine_arcs.py
pylongslit/tests/test_combine_spec.py
pylongslit/tests/test_config.py
pylongslit/tests/test_crr.py
pylongslit/tests/test_data.py
pylongslit/tests/test_extract.py
pylongslit/tests/test_extract_simple.py
pylongslit/tests/test_flats.py
pylongslit/tests/test_flux_calib.py
pylongslit/tests/test_objtrace.py
pylongslit/tests/test_reduce.py
pylongslit/tests/test_sensfunc.py
pylongslit/tests/test_sky.py
pylongslit/tests/test_wavecalib.py
pylongslit/tools/air_to_vac.py
pylongslit/tools/file_cp.sh
pylongslit-1.1.5.dist-info/METADATA
pylongslit-1.1.5.dist-info/WHEEL
pylongslit-1.1.5.dist-info/entry_points.txt
pylongslit-1.1.5.dist-info/top_level.txt
pylongslit-1.1.5.dist-info/RECORD
