Metadata-Version: 2.4
Name: pylongslit
Version: 1.1.5
Summary: PyLongslit is a simple manual Python pipeline for processing astronomical long-slit spectra recorded with CCD detectors.
Home-page: https://kostasvaleckas.github.io/PyLongslit/
Author: Kostas Valeckas
Author-email: kostas.valeckas@nbi.ku.dk
License: MIT
Project-URL: Documentation, https://kostasvaleckas.github.io/PyLongslit/
Project-URL: Source, https://github.com/KostasValeckas/PyLongslit/
Project-URL: Tracker, https://github.com/KostasValeckas/PyLongslit/issues/
Classifier: Development Status :: 4 - Beta
Classifier: Intended Audience :: Science/Research
Classifier: Topic :: Scientific/Engineering :: Astronomy
Requires-Python: >=3.10
Requires-Dist: setuptools
Requires-Dist: astropy>=6.1.7
Requires-Dist: astroscrappy>=1.2.0
Requires-Dist: colorama>=0.4.6
Requires-Dist: matplotlib>=3.10.7
Requires-Dist: numpy<2.0.0,>=1.26.4
Requires-Dist: photutils>=2.0.2
Requires-Dist: PyAstronomy>=0.22.0
Requires-Dist: PyQt5>=5.15.10
Requires-Dist: scikit_learn>=1.6.1
Requires-Dist: scipy>=1.15.2
Requires-Dist: scikit-image>=0.25.2
Requires-Dist: tqdm>=4.67.1
Requires-Dist: PyAstronomy>=0.22.0
Provides-Extra: doc
Requires-Dist: sphinx; extra == "doc"
Requires-Dist: sphinx-rtd-theme; extra == "doc"
Requires-Dist: sphinx-autodoc-typehints; extra == "doc"
Requires-Dist: myst-parser; extra == "doc"
Provides-Extra: test
Requires-Dist: pytest; extra == "test"
Requires-Dist: pytest-order; extra == "test"
Requires-Dist: requests; extra == "test"
Provides-Extra: all
Requires-Dist: sphinx; extra == "all"
Requires-Dist: sphinx-rtd-theme; extra == "all"
Requires-Dist: sphinx-autodoc-typehints; extra == "all"
Requires-Dist: myst-parser; extra == "all"
Requires-Dist: pytest; extra == "all"
Requires-Dist: pytest-order; extra == "all"
Requires-Dist: requests; extra == "all"
